SafoneAPI/__init__.py
SafoneAPI/api.py
SafoneAPI/errors.py
SafoneAPI/results.py
safoneapi-1.0.69.dist-info/licenses/LICENSE
safoneapi-1.0.69.dist-info/METADATA
safoneapi-1.0.69.dist-info/WHEEL
safoneapi-1.0.69.dist-info/top_level.txt
safoneapi-1.0.69.dist-info/RECORD
