Metadata-Version: 2.4
Name: SafoneAPI
Version: 1.0.69
Summary: Asynchronous Python Wrapper For SafoneAPI
Home-page: https://github.com/AsmSafone/SafoneAPI
Author: AsmSafone
Author-email: asmsafone@gmail.com
License: MIT
Project-URL: Homepage, https://api.safone.co
Project-URL: Documentation, https://api.safone.co/docs
Project-URL: Issue Tracker, https://github.com/AsmSafone/SafoneAPI/issues
Keywords: API,SafoneAPI,Safone-API,Safone_API
Classifier: Programming Language :: Python :: 3
Classifier: Programming Language :: Python :: 3.7
Classifier: Programming Language :: Python :: 3.8
Classifier: Programming Language :: Python :: 3.9
Classifier: Programming Language :: Python :: 3.10
Classifier: Programming Language :: Python :: 3.11
Classifier: Development Status :: 5 - Production/Stable
Classifier: License :: OSI Approved :: MIT License
Classifier: Operating System :: OS Independent
Classifier: Intended Audience :: Developers
Classifier: Natural Language :: English
Requires-Python: ~=3.7
License-File: LICENSE
Requires-Dist: aiohttp
Requires-Dist: aiofiles
Requires-Dist: pyrogram
Dynamic: author
Dynamic: author-email
Dynamic: classifier
Dynamic: description
Dynamic: description-content-type
Dynamic: home-page
Dynamic: keywords
Dynamic: license
Dynamic: license-file
Dynamic: project-url
Dynamic: requires-dist
Dynamic: requires-python
Dynamic: summary
